COPYING.LESSER.txt
COPYING.txt
LICENSE.txt
MANIFEST.in
README.txt
setup.py
witkets/__init__.py
witkets/aboutdialog.py
witkets/accellabel.py
witkets/application.py
witkets/cardlayout.py
witkets/colorbutton.py
witkets/consoleview.py
witkets/coordsys.py
witkets/expander.py
witkets/filechooserentry.py
witkets/gauge.py
witkets/imagebutton.py
witkets/imagemap.py
witkets/ipytext.py
witkets/led.py
witkets/ledbar.py
witkets/linkbutton.py
witkets/logicswitch.py
witkets/numericlabel.py
witkets/pyscrolledtext.py
witkets/pytext.py
witkets/ribbon.py
witkets/spin.py
witkets/spinner.py
witkets/style.py
witkets/tank.py
witkets/themedlabelframe.py
witkets/thermometer.py
witkets/timeentry.py
witkets/tkbuilder.py
witkets/togglebutton.py
witkets/toolbar.py
witkets.egg-info/PKG-INFO
witkets.egg-info/SOURCES.txt
witkets.egg-info/dependency_links.txt
witkets.egg-info/top_level.txt
witkets/core/__init__.py
witkets/core/attribspec.py
witkets/core/libraryitem.py
witkets/core/wtk_property.py
witkets/core/wtk_types.py
witkets/data/__init__.py
witkets/data/default_theme.ini
witkets/data/xbm/__init__.py
witkets/data/xbm/arrow-down-16.xbm
witkets/data/xbm/arrow-right-16.xbm
witkets/plot/__init__.py
witkets/plot/plot.py
witkets/plot/plotstyle.py
witkets/plot/scope.py
witkets/plot/scopechannel.py
witkets/plot/series.py
witkets/scripts/__init__.py
witkets/scripts/demo.py
witkets/scripts/quickstart.py