Metadata-Version: 1.0
Name: witkets
Version: 2.1
Summary: Tkinter extensions
Home-page: http://www.leandromattioli.com.br/witkets
Author: Leandro Mattioli
Author-email: leandro.mattioli@gmail.com
License: LGPL
Platform: UNKNOWN
